awsiammapper/__init__.py
awsiammapper/__main__.py
awsiammapper/client.py
awsiammapper/config.py
awsiammapper/mapper.py
awsiammapper/policy.py
awsiammapper/writer.py
awsiammapper-0.1.1.dist-info/LICENSE
awsiammapper-0.1.1.dist-info/METADATA
awsiammapper-0.1.1.dist-info/WHEEL
awsiammapper-0.1.1.dist-info/RECORD
