Metadata-Version: 2.1
Name: awsiammapper
Version: 0.1.1
Summary: 
Author: Jon Paske
Author-email: joncpaske@gmail.com
Requires-Python: >=3.10,<4.0
Classifier: Programming Language :: Python :: 3
Classifier: Programming Language :: Python :: 3.10
Classifier: Programming Language :: Python :: 3.11
Classifier: Programming Language :: Python :: 3.12
Classifier: Programming Language :: Python :: 3.13
Requires-Dist: boto3 (>=1.35.81,<2.0.0)
